__init__.py
smartgenai/__init__.py
smartgenai/ragWrapper.py
smartgenai/connectors/documents/__init__.py
smartgenai/connectors/documents/html.py
smartgenai/connectors/documents/llamaparsePdf.py
smartgenai/connectors/documents/simplePdf.py
smartgenai/connectors/documents/txt.py
smartgenai/connectors/embeddings/__init__.py
smartgenai/connectors/embeddings/ollama.py
smartgenai/connectors/embeddings/sentenceTransformer.py
smartgenai/connectors/llms/AWSBaseModel.py
smartgenai/connectors/llms/__init__.py
smartgenai/connectors/llms/huggingFace.py
smartgenai/connectors/llms/ollama.py
smartgenai/connectors/llms/openai.py
smartgenai/connectors/llms/AWSModels/Claude.py
smartgenai/connectors/llms/AWSModels/Mistral.py
smartgenai/connectors/llms/AWSModels/Titan.py
smartgenai/connectors/llms/AWSModels/__init__.py
smartgenai/connectors/vstore/ChromaDB.py
smartgenai/connectors/vstore/__init__.py
smartgenai/connectors/vstore/faiss.py
smartgenai/framework/__init__.py
smartgenai/framework/objectBase.py
smartgenai/framework/documents/__init__.py
smartgenai/framework/documents/documentBaseObject.py
smartgenai/framework/documents/documentFactory.py
smartgenai/framework/embeddings/__init__.py
smartgenai/framework/embeddings/embedding.py
smartgenai/framework/embeddings/embeddingsBaseObject.py
smartgenai/framework/embeddings/embeddingsFactory.py
smartgenai/framework/llms/LLMBaseObject.py
smartgenai/framework/llms/LLMFactory.py
smartgenai/framework/llms/__init__.py
smartgenai/framework/sets/__init__.py
smartgenai/framework/sets/chunks.py
smartgenai/framework/sets/nearest.py
smartgenai/framework/sets/prompt.py
smartgenai/framework/vstore/__init__.py
smartgenai/framework/vstore/vstoreBaseObject.py
smartgenai/framework/vstore/vstoreFactory.py
smartgenai/interfaces/IChunks.py
smartgenai/interfaces/IDocument.py
smartgenai/interfaces/IEmbeddings.py
smartgenai/interfaces/ILLM.py
smartgenai/interfaces/INearest.py
smartgenai/interfaces/IPrompt.py
smartgenai/interfaces/IRag.py
smartgenai-0.1.0.1.dist-info/LICENSE
smartgenai-0.1.0.1.dist-info/METADATA
smartgenai-0.1.0.1.dist-info/WHEEL
smartgenai-0.1.0.1.dist-info/top_level.txt
smartgenai-0.1.0.1.dist-info/RECORD
